anaouder/__init__.py
anaouder/adskrivan.py
anaouder/istitlan.py
anaouder/linennan.py
anaouder/mikro.py
anaouder/normalizan.py
anaouder/utils.py
anaouder/version.py
anaouder/asr/__init__.py
anaouder/asr/dataset.py
anaouder/asr/inorm_units.tsv
anaouder/asr/models.py
anaouder/asr/post_processing.py
anaouder/asr/postproc_sub.tsv
anaouder/asr/recognizer.py
anaouder/audio/__init__.py
anaouder/dicts/__init__.py
anaouder/dicts/acronyms.tsv
anaouder/dicts/corrected_tokens.tsv
anaouder/dicts/first_names.tsv
anaouder/dicts/last_names.tsv
anaouder/dicts/noun_f.tsv
anaouder/dicts/noun_m.tsv
anaouder/dicts/places.tsv
anaouder/dicts/proper_nouns_phon.tsv
anaouder/dicts/standard_tokens.tsv
anaouder/text/__init__.py
anaouder/text/definitions.py
anaouder/text/inverse_normalizer.py
anaouder/text/moses_br.txt
anaouder/text/normalizer.py
anaouder/text/tokenizer.py
anaouder/text/utils.py
anaouder-1.0.3.data/data/CHANGELOG.md
anaouder-1.0.3.data/data/README-fr.md
anaouder-1.0.3.data/data/README.md
anaouder-1.0.3.dist-info/LICENSE
anaouder-1.0.3.dist-info/METADATA
anaouder-1.0.3.dist-info/WHEEL
anaouder-1.0.3.dist-info/entry_points.txt
anaouder-1.0.3.dist-info/top_level.txt
anaouder-1.0.3.dist-info/RECORD
