Metadata-Version: 2.1
Name: anaouder
Version: 1.0.3
Summary: Breton language speech-to-text tools
Home-page: https://github.com/gweltou/vosk-br
Author: Gweltaz Duval-Guennoc
Author-email: gweltou@hotmail.com
License: MIT
Classifier: Intended Audience :: Developers
Classifier: License :: OSI Approved :: MIT License
Classifier: Programming Language :: Python
Classifier: Programming Language :: Python :: 3
Classifier: Programming Language :: Python :: 3.6
Classifier: Programming Language :: Python :: 3.7
Classifier: Programming Language :: Python :: 3.8
Classifier: Programming Language :: Python :: 3.9
Classifier: Operating System :: OS Independent
Requires-Python: >=3.6.0
License-File: LICENSE
Requires-Dist: static-ffmpeg
Requires-Dist: sounddevice
Requires-Dist: vosk
Requires-Dist: srt
Requires-Dist: jiwer
Requires-Dist: pydub >=0.25.1
Requires-Dist: pytz
Requires-Dist: tqdm ==4.64.1
Requires-Dist: certifi
Requires-Dist: colorama
Requires-Dist: sentence-splitter
Requires-Dist: audioop-lts ; python_version >= "3.13"
